correspondence_tables/__init__.py
correspondence_tables/usepa_to_chemspyder.py
correspondence_tables/bin/__init__.py
correspondence_tables/bin/correspondence_tables_cli.py
correspondence_tables/data/raw/BEC_to_SITCv3.csv
correspondence_tables/data/raw/CN2017_to_SITCv4.csv
correspondence_tables/data/raw/CN_2017_to_PRODCOM_2017.csv
correspondence_tables/data/raw/CPA2008_to_ HS2007.csv
correspondence_tables/data/raw/CPA2008_to_CPCv2.csv
correspondence_tables/data/raw/CPCv2_to_CPA2008.csv
correspondence_tables/data/raw/CPCv2_to_FCL.csv
correspondence_tables/data/raw/CPCv2_to_SITCv4.csv
correspondence_tables/data/raw/Classifications_v_3_3_17.xlsx
correspondence_tables/data/raw/EXIOBASE3_USA_EPA.csv
correspondence_tables/data/raw/EXIOBASExx_to_ecoinvent3.2-elementary_flow_mapping.csv
correspondence_tables/data/raw/EcoinventAct3.2_to_exiobase2.csv
correspondence_tables/data/raw/EcoinventElflow3.2_to_ILCD.csv
correspondence_tables/data/raw/Ecoivent3.2_to_exiobase2.csv
correspondence_tables/data/raw/Exiobase_to_Bentso.csv
correspondence_tables/data/raw/Exiobase_to_USEPA.csv
correspondence_tables/data/raw/Exiobase_v3_3_17_HSUTs_HIOT_product_correspondences.csv
correspondence_tables/data/raw/FAO_vs_EXIOBASE_prod_classification_correspondence.xlsx
correspondence_tables/data/raw/FCL_to_CPCv2.csv
correspondence_tables/data/raw/HS2007_to_CPA2008.csv
correspondence_tables/data/raw/HS2012_to_SITCv4.csv
correspondence_tables/data/raw/ISIC REV. 3 - EXIOBASE2.0.xlsx
correspondence_tables/data/raw/ISIC31_ISIC4.txt
correspondence_tables/data/raw/ISIC_Rev_4_english_structure.txt
correspondence_tables/data/raw/ISICv4_to_NACEv2.csv
correspondence_tables/data/raw/LC_IMPACT_US_EPA.csv
correspondence_tables/data/raw/NACEv2_to_ISICv4.csv
correspondence_tables/data/raw/PROCOM2017_to_CN2017.csv
correspondence_tables/data/raw/SITCv3_to_BEC.csv
correspondence_tables/data/raw/SITCv4_to_CN2017.csv
correspondence_tables/data/raw/SITCv4_to_CPCv2.csv
correspondence_tables/data/raw/SITCv4_to_HS2012.csv
correspondence_tables-0.1.dist-info/LICENSE
correspondence_tables-0.1.dist-info/METADATA
correspondence_tables-0.1.dist-info/WHEEL
correspondence_tables-0.1.dist-info/entry_points.txt
correspondence_tables-0.1.dist-info/top_level.txt
correspondence_tables-0.1.dist-info/RECORD
