Metadata-Version: 2.1
Name: correspondence-tables
Version: 0.1
Summary: Generate the URIs needed for the BONSAI knowledge graph
Home-page: https://github.com/BONSAMURAIS/correspondence_tables
Author: BONSAI team
Author-email: info@bonsai.uno
License: BSD 3-Clause License
Requires-Dist: docopt
Requires-Dist: pandas
Requires-Dist: rdflib
Requires-Dist: xlrd
